Metadata-Version: 2.1
Name: signalsgraphs
Version: 1.1
Summary: Package for signals representation
Home-page: https://github.com/Daniele1602/Segnali.git
Author: Pasulo Daniele
Author-email: daniele.pasulo@marconirovereto.com
License: UNKNOWN
Project-URL: GitHub, https://github.com/Daniele1602/Segnali.git
Platform: UNKNOWN
Classifier: Programming Language :: Python :: 3
Classifier: License :: OSI Approved :: MIT License
Classifier: Operating System :: OS Independent
Requires-Python: >=3.6
